nonebot_plugin_txt2img/__init__.py
nonebot_plugin_txt2img/config.py
nonebot_plugin_txt2img/download.py
nonebot_plugin_txt2img/model.py
nonebot_plugin_txt2img/template.py
nonebot_plugin_txt2img/txt2img.py
nonebot_plugin_txt2img-0.4.1.dist-info/LICENSE
nonebot_plugin_txt2img-0.4.1.dist-info/METADATA
nonebot_plugin_txt2img-0.4.1.dist-info/WHEEL
nonebot_plugin_txt2img-0.4.1.dist-info/RECORD
