Metadata-Version: 2.1
Name: nonebot-plugin-txt2img
Version: 0.4.1
Summary: 轻量文字转图片插件
Home-page: https://github.com/mobyw/nonebot-plugin-txt2img
License: MIT
Keywords: nonebot2,qq,plugin
Author: mobyw
Author-email: mobyw66@gmail.com
Requires-Python: >=3.9,<4.0
Classifier: License :: OSI Approved :: MIT License
Classifier: Programming Language :: Python :: 3
Classifier: Programming Language :: Python :: 3.9
Classifier: Programming Language :: Python :: 3.10
Classifier: Programming Language :: Python :: 3.11
Classifier: Programming Language :: Python :: 3.12
Requires-Dist: nonebot-plugin-localstore (>=0.6.0,<0.7.0)
Requires-Dist: nonebot-plugin-send-anything-anywhere (>=0.5.0,<0.6.0)
Requires-Dist: nonebot2[fastapi,httpx] (>=2.0.0,<3.0.0)
Requires-Dist: pillow (>=10.2.0,<11.0.0)
Requires-Dist: pydantic (>=1.10.5,<2.0.0)
Project-URL: Documentation, https://github.com/mobyw/nonebot-plugin-txt2img/blob/main/README.md
Project-URL: Repository, https://github.com/mobyw/nonebot-plugin-txt2img
